repst.py
setup.py
repst.egg-info/PKG-INFO
repst.egg-info/SOURCES.txt
repst.egg-info/dependency_links.txt
repst.egg-info/not-zip-safe
repst.egg-info/top_level.txt