Metadata-Version: 1.0
Name: repst
Version: 0.9.0
Summary: Nothing... But dont install this
Home-page: UNKNOWN
Author: Neuron Teckid
Author-email: UNKNOWN
License: UNKNOWN
Platform: UNKNOWN
